odoo/addons/product_form_account_move_line_link/README.rst
odoo/addons/product_form_account_move_line_link/__init__.py
odoo/addons/product_form_account_move_line_link/__manifest__.py
odoo/addons/product_form_account_move_line_link/i18n/es.po
odoo/addons/product_form_account_move_line_link/i18n/it.po
odoo/addons/product_form_account_move_line_link/i18n/product_form_account_move_line_link.pot
odoo/addons/product_form_account_move_line_link/i18n/pt_BR.po
odoo/addons/product_form_account_move_line_link/models/__init__.py
odoo/addons/product_form_account_move_line_link/models/product_product.py
odoo/addons/product_form_account_move_line_link/models/product_template.py
odoo/addons/product_form_account_move_line_link/readme/CONTRIBUTORS.md
odoo/addons/product_form_account_move_line_link/readme/DESCRIPTION.md
odoo/addons/product_form_account_move_line_link/readme/USAGE.md
odoo/addons/product_form_account_move_line_link/static/description/icon.png
odoo/addons/product_form_account_move_line_link/static/description/index.html
odoo/addons/product_form_account_move_line_link/tests/__init__.py
odoo/addons/product_form_account_move_line_link/tests/test_product_product.py
odoo/addons/product_form_account_move_line_link/views/account_move_line_views.xml
odoo/addons/product_form_account_move_line_link/views/product_product_views.xml
odoo/addons/product_form_account_move_line_link/views/product_template_views.xml
odoo_addon_product_form_account_move_line_link-18.0.1.0.0.2.dist-info/METADATA
odoo_addon_product_form_account_move_line_link-18.0.1.0.0.2.dist-info/WHEEL
odoo_addon_product_form_account_move_line_link-18.0.1.0.0.2.dist-info/top_level.txt
odoo_addon_product_form_account_move_line_link-18.0.1.0.0.2.dist-info/RECORD
